mensajes/__init__.py
mensajes/adios/__init__.py
mensajes/adios/despedida.py
mensajes/hola/__init__.py
mensajes/hola/saludo.py
mensajes_emimartinha-3.2.dist-info/licenses/LICENSE
mensajes_emimartinha-3.2.dist-info/METADATA
mensajes_emimartinha-3.2.dist-info/WHEEL
mensajes_emimartinha-3.2.dist-info/top_level.txt
mensajes_emimartinha-3.2.dist-info/RECORD
