Metadata-Version: 2.4
Name: mensajes-emimartinha
Version: 3.2
Summary: Un paquete para saludar y despedir
Author-email: Emiliano <emimartinha@gmail.com>
License: MIT License
Classifier: Programming Language :: Python :: 3
Classifier: Programming Language :: Python :: 3.8
Classifier: License :: OSI Approved :: MIT License
Classifier: Operating System :: OS Independent
Classifier: Development Status :: 3 - Alpha
Classifier: Intended Audience :: Developers
Classifier: Topic :: Software Development :: Libraries :: Python Modules
Requires-Python: >=3.8
License-File: LICENSE
Requires-Dist: numpy<2.0,>=1.26
Dynamic: license-file
